setup.cfg
setup.py
tc_force_upscale/__init__.py
tc_force_upscale.egg-info/PKG-INFO
tc_force_upscale.egg-info/SOURCES.txt
tc_force_upscale.egg-info/dependency_links.txt
tc_force_upscale.egg-info/not-zip-safe
tc_force_upscale.egg-info/requires.txt
tc_force_upscale.egg-info/top_level.txt
tc_force_upscale/filters/__init__.py
tc_force_upscale/filters/force_upscale.py