Metadata-Version: 1.1
Name: tc-force-upscale
Version: 0.1.0
Summary: Thumbor filter
Home-page: http://github.com/vvarp/tc_force_upscale
Author: Maciek Szczesniak
Author-email: vvarp@me.com
License: MIT
Platform: any
Classifier: Development Status :: 4 - Beta
Classifier: Intended Audience :: Developers
Classifier: License :: OSI Approved :: MIT License
Classifier: Operating System :: OS Independent
Classifier: Programming Language :: Python
Classifier: Topic :: Software Development :: Libraries :: Python Modules
